LICENSE
MANIFEST.in
README.rst
setup.py
django_initialcon.egg-info/PKG-INFO
django_initialcon.egg-info/SOURCES.txt
django_initialcon.egg-info/dependency_links.txt
django_initialcon.egg-info/top_level.txt
docs/_static/images/p1.png
docs/_static/images/p2.png
docs/_static/images/p3.png
docs/_static/images/p4.png
docs/_static/images/p5.png
docs/_static/images/p6.png
docs/_static/images/p7.png
initialcon/__init__.py