Metadata-Version: 1.1
Name: django-initialcon
Version: 0.1.4
Summary: A small django application for generating small colourful icons for users profile pictures
Home-page: https://github.com/bettsmatt/django-initialcon
Author: Matthew Betts
Author-email: matt.je.betts@gmail.com
License: MIT License
Platform: UNKNOWN
Classifier: Environment :: Web Environment
Classifier: Framework :: Django
Classifier: Intended Audience :: Developers
Classifier: License :: OSI Approved :: BSD License
Classifier: Operating System :: OS Independent
Classifier: Programming Language :: Python
Classifier: Programming Language :: Python :: 2.6
Classifier: Programming Language :: Python :: 2.7
Classifier: Topic :: Internet :: WWW/HTTP
Classifier: Topic :: Internet :: WWW/HTTP :: Dynamic Content
